mlcollect/__init__.py
mlcollect/cnn/__init__.py
mlcollect/cnn/agegendernet.py
mlcollect/cnn/alexnet.py
mlcollect/cnn/deepergooglenet.py
mlcollect/cnn/lenet.py
mlcollect/cnn/minigooglenet.py
mlcollect/cnn/minivggnet.py
mlcollect/cnn/resnet.py
mlcollect/cnn/shallownet.py
mlcollect/data/__init__.py
mlcollect/data/hdf5DatasetWriter.py
mlcollect/meta/__init__.py
mlcollect/meta/siamese.py
mlcollect/meta/siameseTripletLost.py
mlcollect/visualize/__init__.py
mlcollect/visualize/scatter.py
mlcollect-0.0.10.dist-info/LICENSE
mlcollect-0.0.10.dist-info/METADATA
mlcollect-0.0.10.dist-info/WHEEL
mlcollect-0.0.10.dist-info/top_level.txt
mlcollect-0.0.10.dist-info/RECORD
