Metadata-Version: 2.1
Name: mlcollect
Version: 0.0.10
Summary: My machine learning collection
Home-page: https://github.com/sanghuynh1501/mlcollect.git
Author: Huynh Ngoc Sang
Author-email: sanghuynhnt95@gmail.com
License: UNKNOWN
Platform: UNKNOWN
Classifier: Programming Language :: Python :: 3
Classifier: License :: OSI Approved :: MIT License
Classifier: Operating System :: OS Independent
Requires-Dist: tensorflow
Requires-Dist: matplotlib
Requires-Dist: sklearn
Requires-Dist: io
Requires-Dist: h5py
